msgpack_ext/exceptions.py
msgpack_ext/msgpack.py
msgpack_ext-0.1.3.dist-info/DESCRIPTION.rst
msgpack_ext-0.1.3.dist-info/METADATA
msgpack_ext-0.1.3.dist-info/RECORD
msgpack_ext-0.1.3.dist-info/WHEEL
msgpack_ext-0.1.3.dist-info/metadata.json
msgpack_ext-0.1.3.dist-info/pbr.json
msgpack_ext-0.1.3.dist-info/top_level.txt
