Metadata-Version: 2.0
Name: msgpack-ext
Version: 0.1.3
Summary: extended types for msgpack
Home-page: http://msgpack_ext.readthedocs.io/
Author: Zack Buhman
Author-email: zack@buhman.org
License: UNKNOWN
Platform: UNKNOWN
Classifier: Development Status :: 5 - Production/Stable
Classifier: Intended Audience :: Developers
Classifier: License :: OSI Approved :: GNU Affero General Public License v3 or later (AGPLv3+)
Classifier: Operating System :: POSIX :: Linux
Classifier: Programming Language :: Python
Classifier: Programming Language :: Python :: 3 :: Only
Classifier: Programming Language :: Python :: 3.5
Classifier: Programming Language :: Python :: 3.6
Requires-Dist: msgpack-python (>=0.4.8)
Requires-Dist: tblib (>=1.3.2)
